dbautomate/DBAutomate.py
dbautomate/__init__.py
dbautomate/config_file.py
mydblibrary-1.1.2.dist-info/METADATA
mydblibrary-1.1.2.dist-info/WHEEL
mydblibrary-1.1.2.dist-info/top_level.txt
mydblibrary-1.1.2.dist-info/RECORD
