Metadata-Version: 2.1
Name: mydblibrary
Version: 1.1.2
Requires-Dist: psycopg2
